shawnguo/__init__.py
shawnguo/love.py
shawnguo/version.py
shawnguo-0.0.4.dist-info/METADATA
shawnguo-0.0.4.dist-info/WHEEL
shawnguo-0.0.4.dist-info/top_level.txt
shawnguo-0.0.4.dist-info/RECORD
